srse_manchester/__init__.py
srse_manchester/an_ontology.py
srse_manchester/config.py
srse_manchester/ontology_abstract.py
srse_manchester/srse_manchester.py
tests/__init__.py
tests/mock_response.py
tests/test_cases.py
srse_manchester-1.0.1.dist-info/METADATA
srse_manchester-1.0.1.dist-info/WHEEL
srse_manchester-1.0.1.dist-info/top_level.txt
srse_manchester-1.0.1.dist-info/RECORD
