Metadata-Version: 2.1
Name: srse-manchester
Version: 1.0.1
Summary: My Ontology Lookup Service
Home-page: https://github.com/sabadijou/srse_manchester/
Author: Sadegh Abadijou
Author-email: s.abadijou@gmail.com
License: MIT
Classifier: Programming Language :: Python :: 3
Classifier: License :: OSI Approved :: MIT License
Requires-Dist: certifi ==2023.11.17
Requires-Dist: charset-normalizer ==3.3.2
Requires-Dist: colorama ==0.4.6
Requires-Dist: coverage ==7.4.0
Requires-Dist: exceptiongroup ==1.2.0
Requires-Dist: idna ==3.6
Requires-Dist: iniconfig ==2.0.0
Requires-Dist: packaging ==23.2
Requires-Dist: pluggy ==1.3.0
Requires-Dist: pytest ==7.4.4
Requires-Dist: pytest-cov ==4.1.0
Requires-Dist: requests ==2.31.0
Requires-Dist: tomli ==2.0.1
Requires-Dist: urllib3 ==2.1.0
